cv2/config.py
cv2/load_config_py3.py
cv2/LICENSE.txt
cv2/config-3.8.py
cv2/LICENSE-3RD-PARTY.txt
cv2/version.py
cv2/cv2.cpython-38-x86_64-linux-gnu.so
cv2/__init__.py
cv2/load_config_py2.py
cv2/data/haarcascade_frontalface_alt2.xml
cv2/data/haarcascade_frontalface_alt_tree.xml
cv2/data/haarcascade_eye_tree_eyeglasses.xml
cv2/data/haarcascade_smile.xml
cv2/data/haarcascade_frontalcatface_extended.xml
cv2/data/haarcascade_frontalface_default.xml
cv2/data/haarcascade_profileface.xml
cv2/data/haarcascade_fullbody.xml
cv2/data/haarcascade_upperbody.xml
cv2/data/haarcascade_frontalface_alt.xml
cv2/data/haarcascade_lowerbody.xml
cv2/data/haarcascade_russian_plate_number.xml
cv2/data/haarcascade_frontalcatface.xml
cv2/data/haarcascade_licence_plate_rus_16stages.xml
cv2/data/haarcascade_eye.xml
cv2/data/haarcascade_righteye_2splits.xml
cv2/data/haarcascade_lefteye_2splits.xml
cv2/data/__init__.py
cv2/mat_wrapper/__init__.py
cv2/gapi/__init__.py
cv2/qt/fonts/DejaVuSans-Bold.ttf
cv2/qt/fonts/DejaVuSans-ExtraLight.ttf
cv2/qt/fonts/DejaVuSans-Oblique.ttf
cv2/qt/fonts/DejaVuSansCondensed.ttf
cv2/qt/fonts/DejaVuSans.ttf
cv2/qt/fonts/DejaVuSansCondensed-Bold.ttf
cv2/qt/fonts/DejaVuSans-BoldOblique.ttf
cv2/qt/fonts/DejaVuSansCondensed-BoldOblique.ttf
cv2/qt/fonts/DejaVuSansCondensed-Oblique.ttf
cv2/qt/plugins/platforms/libqxcb.so
cv2/utils/__init__.py
cv2/misc/version.py
cv2/misc/__init__.py
opencv_python_asen.libs/libcrypto-018b8c17.so.1.1
opencv_python_asen.libs/libssl-6082116c.so.1.1
opencv_python_asen.libs/libz-745e0a09.so.1.2.7
opencv_python_asen.libs/libX11-xcb-69166bdf.so.1.0.0
opencv_python_asen.libs/libQt5Test-c38a5234.so.5.15.0
opencv_python_asen.libs/libxcb-icccm-413c9f41.so.4.0.0
opencv_python_asen.libs/libxcb-render-util-43ce00f5.so.0.0.0
opencv_python_asen.libs/libxcb-util-4d666913.so.1.0.0
opencv_python_asen.libs/libxcb-xfixes-9be3ba6f.so.0.0.0
opencv_python_asen.libs/libQt5Gui-ba0a2070.so.5.15.0
opencv_python_asen-4.5.10.dist-info/RECORD
opencv_python_asen-4.5.10.dist-info/LICENSE.txt
opencv_python_asen-4.5.10.dist-info/WHEEL
opencv_python_asen-4.5.10.dist-info/LICENSE-3RD-PARTY.txt
opencv_python_asen-4.5.10.dist-info/top_level.txt
opencv_python_asen-4.5.10.dist-info/METADATA
